sussy_baka/__init__.py
sussy_baka-0.0.1.dist-info/LICENSE
sussy_baka-0.0.1.dist-info/METADATA
sussy_baka-0.0.1.dist-info/WHEEL
sussy_baka-0.0.1.dist-info/top_level.txt
sussy_baka-0.0.1.dist-info/RECORD
