Metadata-Version: 2.1
Name: sussy-baka
Version: 0.0.1
Summary: For all your very sussy needs
Author-email: Very Sus Person <verysusman@sussytown.com>
Project-URL: Homepage, https://www.example.com
Project-URL: Bug Tracker, https://devnull-as-a-service.com
Classifier: Programming Language :: Python :: 3
Classifier: License :: OSI Approved :: MIT License
Classifier: Operating System :: OS Independent
Requires-Python: >=3.7
License-File: LICENSE
